gnukek/__init__.py
gnukek/backends/__init__.py
gnukek/backends/decryption.py
gnukek/backends/encryption.py
gnukek/backends/v1.py
gnukek/constants.py
gnukek/exceptions.py
gnukek/helpers.py
gnukek/keys.py
gnukek/py.typed
gnukek/utils.py
gnukek-2.0.0.dist-info/LICENSE
gnukek-2.0.0.dist-info/METADATA
gnukek-2.0.0.dist-info/WHEEL
gnukek-2.0.0.dist-info/RECORD
