Metadata-Version: 2.3
Name: gnukek
Version: 2.0.0
Summary: Key Encryption Key
License: GPL-3.0-only
Author: SweetBubaleXXX
Author-email: 70811772+SweetBubaleXXX@users.noreply.github.com
Requires-Python: >=3.10,<4.0
Classifier: License :: OSI Approved :: GNU General Public License v3 (GPLv3)
Classifier: Programming Language :: Python :: 3
Classifier: Programming Language :: Python :: 3.10
Classifier: Programming Language :: Python :: 3.11
Classifier: Programming Language :: Python :: 3.12
Classifier: Programming Language :: Python :: 3.13
Requires-Dist: cffi (>=1.17,<2.0)
Requires-Dist: cryptography (>=40,<43)
